{
  "original_path": "/Volumes/Akron/INTAKE/AKRON/sys_darwin.go",
  "original_name": "sys_darwin.go",
  "file_type": ".go",
  "mime_type": "application/octet-stream",
  "size_bytes": 2842,
  "content_hash": "d98855e0b4af1316c898a9d378a28fb0d5867544bcfa6845646842e3daf0d061",
  "semantic_fingerprint": "sys_darwin",
  "detected_at": "2025-11-13T05:18:47.882913",
  "suggested_field": "development",
  "suggested_name": "development_20251113_sys_darwin_d98855e0.go",
  "original_metadata": {
    "size": 2842,
    "modified": "2025-01-12T09:30:45.804874",
    "created": "2025-11-11T03:39:11.708311"
  },
  "stripped_metadata": {}
}