{
  "original_path": "/Volumes/Akron/INTAKE/AKRON/vary_day.go",
  "original_name": "vary_day.go",
  "file_type": ".go",
  "mime_type": "application/octet-stream",
  "size_bytes": 690,
  "content_hash": "033946460887c44d617d6d786574c914acf67363afbed9b28a3f33da1e1c12ed",
  "semantic_fingerprint": "vary_day",
  "detected_at": "2025-11-13T05:18:46.112201",
  "suggested_field": "development",
  "suggested_name": "development_20251113_vary_day_03394646.go",
  "original_metadata": {
    "size": 690,
    "modified": "2025-01-12T09:30:47.727146",
    "created": "2025-11-11T03:39:11.674461"
  },
  "stripped_metadata": {}
}