{
  "original_path": "/Volumes/Akron/INTAKE/AKRON/slice2array.go",
  "original_name": "slice2array.go",
  "file_type": ".go",
  "mime_type": "application/octet-stream",
  "size_bytes": 1963,
  "content_hash": "9c85c57281bf2004a5652774ac8eb4d019ce842db1a9108237bc593be985bf96",
  "semantic_fingerprint": "slice2array",
  "detected_at": "2025-11-13T05:18:46.925756",
  "suggested_field": "development",
  "suggested_name": "development_20251113_slice2array_9c85c572.go",
  "original_metadata": {
    "size": 1963,
    "modified": "2025-01-12T09:30:47.827981",
    "created": "2025-11-11T03:39:11.689650"
  },
  "stripped_metadata": {}
}