{
  "original_path": "/Volumes/Akron/INTAKE/AKRON/sizes.go",
  "original_name": "sizes.go",
  "file_type": ".go",
  "mime_type": "application/octet-stream",
  "size_bytes": 9028,
  "content_hash": "f291d2a0fdc9f9ec0c48f9538aa4ec20803038c021600c9b256aca5e19b8ec42",
  "semantic_fingerprint": "sizes",
  "detected_at": "2025-11-13T05:18:46.432459",
  "suggested_field": "development",
  "suggested_name": "development_20251113_sizes_f291d2a0.go",
  "original_metadata": {
    "size": 9028,
    "modified": "2025-01-12T09:30:44.504460",
    "created": "2025-11-11T03:39:11.681531"
  },
  "stripped_metadata": {}
}