{
  "original_path": "/Volumes/Akron/INTAKE/AKRON/composition.go",
  "original_name": "composition.go",
  "file_type": ".go",
  "mime_type": "application/octet-stream",
  "size_bytes": 14452,
  "content_hash": "3d1be52960f2693926472819b747646e7d2371d2bb5f53097cf9d46c913052df",
  "semantic_fingerprint": "composition",
  "detected_at": "2025-11-13T05:18:47.976590",
  "suggested_field": "development",
  "suggested_name": "development_20251113_composition_3d1be529.go",
  "original_metadata": {
    "size": 14452,
    "modified": "2025-01-12T09:30:45.818291",
    "created": "2025-11-11T03:39:11.709980"
  },
  "stripped_metadata": {}
}