{
  "original_path": "/Volumes/Akron/INTAKE/AKRON/multiline.toml",
  "original_name": "multiline.toml",
  "file_type": ".toml",
  "mime_type": "application/octet-stream",
  "size_bytes": 596,
  "content_hash": "d12fc2961c56f0bc029e8734034ddeeab78bfaa188b3f0af6d960b7f98d9adc4",
  "semantic_fingerprint": "multiline",
  "detected_at": "2025-11-13T05:18:46.031578",
  "suggested_field": "data_sovereignty",
  "suggested_name": "data_sovereignty_20251113_multiline_d12fc296.toml",
  "original_metadata": {
    "size": 596,
    "modified": "2025-01-12T09:30:51.664114",
    "created": "2025-11-11T03:39:11.672565"
  },
  "stripped_metadata": {}
}